microcosm_logging/__init__.py
microcosm_logging/decorators.py
microcosm_logging/factories.py
microcosm_logging/formatters.py
microcosm_logging/levels.py
microcosm_logging/timing.py
microcosm_logging-2.0.0.dist-info/LICENSE
microcosm_logging-2.0.0.dist-info/METADATA
microcosm_logging-2.0.0.dist-info/WHEEL
microcosm_logging-2.0.0.dist-info/entry_points.txt
microcosm_logging-2.0.0.dist-info/top_level.txt
microcosm_logging-2.0.0.dist-info/RECORD
